setup.py
gitdepot/__init__.py
gitdepot/parser.py
gitdepot.egg-info/PKG-INFO
gitdepot.egg-info/SOURCES.txt
gitdepot.egg-info/dependency_links.txt
gitdepot.egg-info/entry_points.txt
gitdepot.egg-info/requires.txt
gitdepot.egg-info/top_level.txt