Metadata-Version: 1.0
Name: gitdepot
Version: 0.1.32
Summary: A simple git repository management system
Home-page: http://rescrv.net/
Author: Robert Escriva
Author-email: robert@rescrv.net
License: BSD
Keywords: git
Platform: UNKNOWN
